dell_ai/__init__.py
dell_ai/__main__.py
dell_ai/apps.py
dell_ai/auth.py
dell_ai/client.py
dell_ai/constants.py
dell_ai/exceptions.py
dell_ai/models.py
dell_ai/platforms.py
dell_ai/cli/__init__.py
dell_ai/cli/main.py
dell_ai/cli/utils.py
dell_ai-0.1.4.dist-info/METADATA
dell_ai-0.1.4.dist-info/WHEEL
dell_ai-0.1.4.dist-info/entry_points.txt
dell_ai-0.1.4.dist-info/licenses/LICENSE
dell_ai-0.1.4.dist-info/RECORD
