Metadata-Version: 2.4
Name: dell-ai
Version: 0.1.4
Summary: Python SDK and CLI for interacting with the Dell Enterprise Hub (DEH)
Project-URL: Repository, https://github.com/huggingface/dell-ai
Project-URL: Homepage, https://dell.huggingface.co/
Maintainer-email: Andrew Reed <andrew.reed@huggingface.co>, Alvaro Bartolome <alvaro.bartolome@huggingface.co>
License: Apache-2.0
License-File: LICENSE
Classifier: License :: OSI Approved :: Apache Software License
Classifier: Programming Language :: Python :: 3
Classifier: Programming Language :: Python :: 3.10
Classifier: Programming Language :: Python :: 3.11
Requires-Python: >=3.10
Requires-Dist: huggingface-hub>=0.30.2
Requires-Dist: pydantic>=2.5.0
Requires-Dist: requests>=2.31.0
Requires-Dist: typer>=0.9.0
Provides-Extra: dev
Requires-Dist: black>=23.3.0; extra == 'dev'
Requires-Dist: bump2version>=1.0.1; extra == 'dev'
Requires-Dist: flake8>=6.0.0; extra == 'dev'
Requires-Dist: ipykernel>=6.29.5; extra == 'dev'
Requires-Dist: isort>=5.12.0; extra == 'dev'
Requires-Dist: pytest-cov>=4.1.0; extra == 'dev'
Requires-Dist: pytest-mock>=3.10.0; extra == 'dev'
Requires-Dist: pytest>=7.4.0; extra == 'dev'
